Metadata-Version: 2.1
Name: d3tools-alpha
Version: 0.1.2
Summary: Version Alpha de d3tools
Home-page: https://github.com/djulcac/d3tools
Author: Danny Julca C.
Author-email: djulcac@uni.pe
Project-URL: Bug Tracker, https://github.com/djulcac/d3tools/issues
Classifier: Programming Language :: Python :: 3
Classifier: License :: OSI Approved :: MIT License
Classifier: Operating System :: OS Independent
Requires-Python: >=3.6
License-File: LICENSE
Requires-Dist: pandas (>=0.20.3)
Requires-Dist: psycopg2 (>=2.9.3)
